CHANGES.txt
CONTRIBUTORS.txt
MANIFEST.in
README.rst
setup.py
docs/LICENSE.GPL
docs/LICENSE.txt
src/collective/__init__.py
src/collective.delegatesiteadmin.egg-info/PKG-INFO
src/collective.delegatesiteadmin.egg-info/SOURCES.txt
src/collective.delegatesiteadmin.egg-info/dependency_links.txt
src/collective.delegatesiteadmin.egg-info/entry_points.txt
src/collective.delegatesiteadmin.egg-info/namespace_packages.txt
src/collective.delegatesiteadmin.egg-info/not-zip-safe
src/collective.delegatesiteadmin.egg-info/requires.txt
src/collective.delegatesiteadmin.egg-info/top_level.txt
src/collective/delegatesiteadmin/__init__.py
src/collective/delegatesiteadmin/configure.zcml
src/collective/delegatesiteadmin/sharing.py
src/collective/delegatesiteadmin/testing.py
src/collective/delegatesiteadmin/locales/fr/LC_MESSAGES/plone.po
src/collective/delegatesiteadmin/locales/nl/LC_MESSAGES/plone.po
src/collective/delegatesiteadmin/profiles/default/metadata.xml
src/collective/delegatesiteadmin/profiles/default/rolemap.xml
src/collective/delegatesiteadmin/tests/__init__.py
src/collective/delegatesiteadmin/tests/test_example.py