Metadata-Version: 1.1
Name: collective.delegatesiteadmin
Version: 0.1.2
Summary: Plone : Delegation of Site Administrator role through sharing tab
Home-page: https://github.com/collective/collective.delegatesiteadmin
Author: Godefroid Chapelle
Author-email: gotcha@bubblenet.be
License: gpl
Platform: UNKNOWN
Classifier: Environment :: Web Environment
Classifier: Operating System :: OS Independent
Classifier: Framework :: Zope2
Classifier: Framework :: Plone
Classifier: Framework :: Plone :: 4.2
Classifier: Framework :: Plone :: 4.3
Classifier: Programming Language :: Python
Classifier: Programming Language :: Python :: 2.6
Classifier: Programming Language :: Python :: 2.7
Classifier: Topic :: Software Development :: Libraries :: Python Modules
